{
  "name": "wefabric/uitgelicht-medewerkersverhaal",
  "title": "Uitgelicht medewerkersverhaal",
  "description": "Een uitgelicht medewerkersverhaal blok",
  "category": "wefabric-theme",
  "icon": "format-status",
  "apiVersion": 3,
  "keywords": [
    "Uitgelicht mederwerkersverhaal"
  ],
  "acf": {
    "mode": "auto",
    "renderTemplate": "render.php",
    "blockVersion": 3
  },
  "attributes": {},
  "example": {
    "attributes": {
      "data": {
        "text": "This is an example text field",
        "text_area": "This is an example text area field"
      }
    }
  }
}
